jupyter_aws/__init__.py
jupyter_aws/_version.py
jupyter_aws/handlers.py
jupyter_aws/tests/__init__.py
jupyter_aws/tests/test_handlers.py
jupyter_aws-0.0.2.data/data/etc/jupyter/jupyter_notebook_config.d/jupyter_aws.json
jupyter_aws-0.0.2.data/data/etc/jupyter/jupyter_server_config.d/jupyter_aws.json
jupyter_aws-0.0.2.data/data/share/jupyter/labextensions/@datalayer/jupyter-aws/build_log.json
jupyter_aws-0.0.2.data/data/share/jupyter/labextensions/@datalayer/jupyter-aws/package.json
jupyter_aws-0.0.2.data/data/share/jupyter/labextensions/@datalayer/jupyter-aws/schemas/@datalayer/jupyter-admin/package.json.orig
jupyter_aws-0.0.2.data/data/share/jupyter/labextensions/@datalayer/jupyter-aws/schemas/@datalayer/jupyter-admin/plugin.json
jupyter_aws-0.0.2.data/data/share/jupyter/labextensions/@datalayer/jupyter-aws/static/lib_index_js.4348b810ae8dc12e002f.js
jupyter_aws-0.0.2.data/data/share/jupyter/labextensions/@datalayer/jupyter-aws/static/lib_index_js.4348b810ae8dc12e002f.js.map
jupyter_aws-0.0.2.data/data/share/jupyter/labextensions/@datalayer/jupyter-aws/static/remoteEntry.60045aa25abfdbe55e4f.js
jupyter_aws-0.0.2.data/data/share/jupyter/labextensions/@datalayer/jupyter-aws/static/remoteEntry.60045aa25abfdbe55e4f.js.map
jupyter_aws-0.0.2.data/data/share/jupyter/labextensions/@datalayer/jupyter-aws/static/style.js
jupyter_aws-0.0.2.data/data/share/jupyter/labextensions/@datalayer/jupyter-aws/static/style_index_js.09ea6e1de3ce833faf40.js
jupyter_aws-0.0.2.data/data/share/jupyter/labextensions/@datalayer/jupyter-aws/static/style_index_js.09ea6e1de3ce833faf40.js.map
jupyter_aws-0.0.2.data/data/share/jupyter/labextensions/@datalayer/jupyter-aws/static/vendors-node_modules_css-loader_dist_runtime_api_js-node_modules_css-loader_dist_runtime_cssW-72eba1.bac0ab4f283009af8f3d.js
jupyter_aws-0.0.2.dist-info/METADATA
jupyter_aws-0.0.2.dist-info/WHEEL
jupyter_aws-0.0.2.dist-info/licenses/LICENSE
jupyter_aws-0.0.2.dist-info/RECORD
